ocs_authentication/__init__.py
ocs_authentication/auth_profile/__init__.py
ocs_authentication/auth_profile/admin.py
ocs_authentication/auth_profile/apps.py
ocs_authentication/auth_profile/migrations/0001_initial.py
ocs_authentication/auth_profile/migrations/__init__.py
ocs_authentication/auth_profile/models.py
ocs_authentication/auth_profile/test_login.py
ocs_authentication/auth_profile/urls.py
ocs_authentication/auth_profile/views.py
ocs_authentication/backends.py
ocs_authentication/exceptions.py
ocs_authentication/permissions.py
ocs_authentication/settings.py
ocs_authentication/util.py
ocs_authentication-0.2.2.dist-info/LICENSE
ocs_authentication-0.2.2.dist-info/METADATA
ocs_authentication-0.2.2.dist-info/WHEEL
ocs_authentication-0.2.2.dist-info/RECORD
