Metadata-Version: 2.1
Name: ocs-authentication
Version: 0.2.2
Summary: Authentication backends and utilities for the OCS applications
Home-page: https://github.com/observatorycontrolsystem/ocs-authentication
License: GPL-3.0-only
Author: Observatory Control System Project
Author-email: ocs@lco.global
Requires-Python: >=3.8,<4.0
Classifier: License :: OSI Approved :: GNU General Public License v3 (GPLv3)
Classifier: Programming Language :: Python :: 3
Classifier: Programming Language :: Python :: 3.8
Classifier: Programming Language :: Python :: 3.9
Classifier: Programming Language :: Python :: 3.10
Classifier: Programming Language :: Python :: 3.11
Requires-Dist: django (>=4,<5)
Requires-Dist: djangorestframework (>=3.13,<4.0)
Requires-Dist: requests (>=2,<3)
